apbs_binary/__init__.py
apbs_binary/executable.py
apbs_binary/executable.pyi
apbs_binary/bin/analysis
apbs_binary/bin/apbs
apbs_binary/bin/benchmark
apbs_binary/bin/born
apbs_binary/bin/coulomb
apbs_binary/bin/del2dx
apbs_binary/bin/dx2mol
apbs_binary/bin/dx2uhbd
apbs_binary/bin/dxmath
apbs_binary/bin/mergedx
apbs_binary/bin/mergedx2
apbs_binary/bin/mgmesh
apbs_binary/bin/multivalue
apbs_binary/bin/similarity
apbs_binary/bin/smooth
apbs_binary/bin/tensor2dx
apbs_binary/bin/uhbd_asc2bin
apbs_binary/bin/value
apbs_binary/lib/libmetis.dylib
apbs_binary-3.4.1.1.dist-info/LICENSE
apbs_binary-3.4.1.1.dist-info/METADATA
apbs_binary-3.4.1.1.dist-info/WHEEL
apbs_binary-3.4.1.1.dist-info/top_level.txt
apbs_binary-3.4.1.1.dist-info/RECORD
