Metadata-Version: 2.1
Name: apbs-binary
Version: 3.4.1.1
Summary: Install apbs with pip
Author: Kiyoon Kim
License: Apache License
Project-URL: Homepage, https://github.com/deargen/py-apbs-binary
Keywords: biology
Classifier: Programming Language :: Python :: Implementation :: CPython
Classifier: Programming Language :: Python
Classifier: Programming Language :: Python :: 3
Classifier: Programming Language :: Python :: 3.8
Classifier: Programming Language :: Python :: 3.9
Classifier: Programming Language :: Python :: 3.10
Classifier: Programming Language :: Python :: 3.11
Classifier: Programming Language :: Python :: 3.12
Classifier: Programming Language :: Python :: 3.13
Classifier: License :: OSI Approved :: Apache Software License
Requires-Python: <4,>=3.8
License-File: LICENSE
